{
  "children" : [
    {
      "id" : 5888531154642937198,
      "name" : "Window Context Entity, <UIWindow: 0x108207900>",
      "children" : [
        {
          "id" : 6271737036310454313,
          "entityType" : {
            "entity" : {

            }
          },
          "components" : [
            {
              "synchronizationComponent" : {
                "_0" : {

                }
              }
            },
            {
              "transform" : {
                "_0" : {

                }
              }
            }
          ],
          "name" : "<UIWindow: 0x108207900>",
          "children" : [
            {
              "children" : [
                {
                  "parentID" : 14962159650569175068,
                  "name" : "CALayerEntity (unnamed)",
                  "components" : [
                    {
                      "synchronizationComponent" : {
                        "_0" : {

                        }
                      }
                    },
                    {
                      "transform" : {
                        "_0" : {

                        }
                      }
                    }
                  ],
                  "entityType" : {
                    "entity" : {

                    }
                  },
                  "children" : [
                    {
                      "name" : "CALayerEntity (unnamed)",
                      "parentID" : 6834398169344622888,
                      "children" : [
                        {
                          "entityType" : {
                            "entity" : {

                            }
                          },
                          "id" : 1004157965472580030,
                          "parentID" : 2076846966725276874,
                          "name" : "",
                          "components" : [
                            {
                              "synchronizationComponent" : {
                                "_0" : {

                                }
                              }
                            },
                            {
                              "transform" : {
                                "_0" : {

                                }
                              }
                            }
                          ],
                          "children" : [
                            {
                              "entityType" : {
                                "entity" : {

                                }
                              },
                              "components" : [
                                {
                                  "synchronizationComponent" : {
                                    "_0" : {

                                    }
                                  }
                                },
                                {
                                  "transform" : {
                                    "_0" : {

                                    }
                                  }
                                }
                              ],
                              "name" : "",
                              "children" : [
                                {
                                  "children" : [

                                  ],
                                  "parentID" : 1036468274733119706,
                                  "entityType" : {
                                    "entity" : {

                                    }
                                  },
                                  "components" : [
                                    {
                                      "accessibilityComponent" : {
                                        "_0" : {

                                        }
                                      }
                                    },
                                    {
                                      "synchronizationComponent" : {
                                        "_0" : {

                                        }
                                      }
                                    },
                                    {
                                      "transform" : {
                                        "_0" : {

                                        }
                                      }
                                    }
                                  ],
                                  "id" : 11871399037105675462,
                                  "name" : "__realityCheck"
                                }
                              ],
                              "id" : 1036468274733119706,
                              "parentID" : 1004157965472580030
                            }
                          ]
                        }
                      ],
                      "components" : [
                        {
                          "synchronizationComponent" : {
                            "_0" : {

                            }
                          }
                        },
                        {
                          "transform" : {
                            "_0" : {

                            }
                          }
                        }
                      ],
                      "entityType" : {
                        "entity" : {

                        }
                      },
                      "id" : 2076846966725276874
                    },
                    {
                      "parentID" : 6834398169344622888,
                      "entityType" : {
                        "entity" : {

                        }
                      },
                      "children" : [
                        {
                          "id" : 9187504431149601376,
                          "components" : [
                            {
                              "synchronizationComponent" : {
                                "_0" : {

                                }
                              }
                            },
                            {
                              "transform" : {
                                "_0" : {

                                }
                              }
                            }
                          ],
                          "entityType" : {
                            "entity" : {

                            }
                          },
                          "children" : [
                            {
                              "entityType" : {
                                "entity" : {

                                }
                              },
                              "children" : [
                                {
                                  "components" : [
                                    {
                                      "synchronizationComponent" : {
                                        "_0" : {

                                        }
                                      }
                                    },
                                    {
                                      "transform" : {
                                        "_0" : {

                                        }
                                      }
                                    }
                                  ],
                                  "name" : "",
                                  "children" : [
                                    {
                                      "entityType" : {
                                        "entity" : {

                                        }
                                      },
                                      "name" : "Root",
                                      "parentID" : 386378843039366028,
                                      "children" : [
                                        {
                                          "components" : [
                                            {
                                              "synchronizationComponent" : {
                                                "_0" : {

                                                }
                                              }
                                            },
                                            {
                                              "transform" : {
                                                "_0" : {

                                                }
                                              }
                                            }
                                          ],
                                          "id" : 1752955006943905815,
                                          "name" : "Root",
                                          "children" : [
                                            {
                                              "components" : [
                                                {
                                                  "synchronizationComponent" : {
                                                    "_0" : {

                                                    }
                                                  }
                                                },
                                                {
                                                  "transform" : {
                                                    "_0" : {

                                                    }
                                                  }
                                                }
                                              ],
                                              "id" : 6708749681417241735,
                                              "children" : [

                                              ],
                                              "parentID" : 1752955006943905815,
                                              "entityType" : {
                                                "entity" : {

                                                }
                                              },
                                              "name" : "GridMaterial"
                                            },
                                            {
                                              "components" : [
                                                {
                                                  "collisionComponent" : {
                                                    "_0" : {

                                                    }
                                                  }
                                                },
                                                {
                                                  "inputTargetComponent" : {
                                                    "_0" : {

                                                    }
                                                  }
                                                },
                                                {
                                                  "modelComponent" : {
                                                    "_0" : {

                                                    }
                                                  }
                                                },
                                                {
                                                  "synchronizationComponent" : {
                                                    "_0" : {

                                                    }
                                                  }
                                                },
                                                {
                                                  "transform" : {
                                                    "_0" : {

                                                    }
                                                  }
                                                }
                                              ],
                                              "children" : [

                                              ],
                                              "entityType" : {
                                                "modelEntity" : {

                                                }
                                              },
                                              "parentID" : 1752955006943905815,
                                              "id" : 14864102377952482624,
                                              "name" : "Sphere"
                                            }
                                          ],
                                          "parentID" : 9929542333997709463,
                                          "entityType" : {
                                            "entity" : {

                                            }
                                          }
                                        }
                                      ],
                                      "id" : 9929542333997709463,
                                      "components" : [
                                        {
                                          "inputTargetComponent" : {
                                            "_0" : {

                                            }
                                          }
                                        },
                                        {
                                          "synchronizationComponent" : {
                                            "_0" : {

                                            }
                                          }
                                        },
                                        {
                                          "transform" : {
                                            "_0" : {

                                            }
                                          }
                                        }
                                      ]
                                    }
                                  ],
                                  "parentID" : 10331224821125418389,
                                  "id" : 386378843039366028,
                                  "entityType" : {
                                    "entity" : {

                                    }
                                  }
                                }
                              ],
                              "name" : "",
                              "id" : 10331224821125418389,
                              "parentID" : 9187504431149601376,
                              "components" : [
                                {
                                  "synchronizationComponent" : {
                                    "_0" : {

                                    }
                                  }
                                },
                                {
                                  "transform" : {
                                    "_0" : {

                                    }
                                  }
                                }
                              ]
                            }
                          ],
                          "name" : "",
                          "parentID" : 11218566285172561958
                        }
                      ],
                      "components" : [
                        {
                          "synchronizationComponent" : {
                            "_0" : {

                            }
                          }
                        },
                        {
                          "transform" : {
                            "_0" : {

                            }
                          }
                        }
                      ],
                      "name" : "CALayerEntity (unnamed)",
                      "id" : 11218566285172561958
                    }
                  ],
                  "id" : 6834398169344622888
                }
              ],
              "entityType" : {
                "entity" : {

                }
              },
              "components" : [
                {
                  "synchronizationComponent" : {
                    "_0" : {

                    }
                  }
                },
                {
                  "transform" : {
                    "_0" : {

                    }
                  }
                }
              ],
              "id" : 14962159650569175068,
              "name" : "CALayerEntity (unnamed)",
              "parentID" : 6271737036310454313
            }
          ],
          "parentID" : 5888531154642937198
        }
      ],
      "entityType" : {
        "entity" : {

        }
      },
      "components" : [
        {
          "synchronizationComponent" : {
            "_0" : {

            }
          }
        },
        {
          "transform" : {
            "_0" : {

            }
          }
        }
      ]
    }
  ]
}
